[
  {
    "preset": "no_regime",
    "note": "v7-equivalent control.",
    "report_path": "/Users/naufalrachmandani/Library/Application Support/net.metaquotes.wine.metatrader5/drive_c/Program Files/MetaTrader 5/Reports/InvictusForward1M15_v8_round1_no_regime_XAUUSDc_M15_20260101_20260415.htm",
    "net_profit": 28.11,
    "profit_pct": 28.110000000000003,
    "profit_factor": 1.79,
    "expected_payoff": 0.4,
    "total_trades": 71,
    "win_rate": 60.56,
    "balance_dd_pct": 8.36,
    "equity_dd_pct": 9.08
  },
  {
    "preset": "regime_default",
    "note": "Default bearish regime switch.",
    "report_path": "/Users/naufalrachmandani/Library/Application Support/net.metaquotes.wine.metatrader5/drive_c/Program Files/MetaTrader 5/Reports/InvictusForward1M15_v8_round1_regime_default_XAUUSDc_M15_20260101_20260415.htm",
    "net_profit": 28.68,
    "profit_pct": 28.68,
    "profit_factor": 1.85,
    "expected_payoff": 0.41,
    "total_trades": 70,
    "win_rate": 57.14,
    "balance_dd_pct": 7.08,
    "equity_dd_pct": 7.82
  },
  {
    "preset": "regime_soft",
    "note": "Softer bearish regime buy suppression.",
    "report_path": "/Users/naufalrachmandani/Library/Application Support/net.metaquotes.wine.metatrader5/drive_c/Program Files/MetaTrader 5/Reports/InvictusForward1M15_v8_round1_regime_soft_XAUUSDc_M15_20260101_20260415.htm",
    "net_profit": 28.44,
    "profit_pct": 28.439999999999998,
    "profit_factor": 1.83,
    "expected_payoff": 0.41,
    "total_trades": 70,
    "win_rate": 57.14,
    "balance_dd_pct": 7.34,
    "equity_dd_pct": 8.07
  },
  {
    "preset": "regime_hard",
    "note": "Hard bearish mode with stronger buy suppression and sell boost.",
    "report_path": "/Users/naufalrachmandani/Library/Application Support/net.metaquotes.wine.metatrader5/drive_c/Program Files/MetaTrader 5/Reports/InvictusForward1M15_v8_round1_regime_hard_XAUUSDc_M15_20260101_20260415.htm",
    "net_profit": 29.27,
    "profit_pct": 29.270000000000003,
    "profit_factor": 1.85,
    "expected_payoff": 0.42,
    "total_trades": 69,
    "win_rate": 57.97,
    "balance_dd_pct": 6.65,
    "equity_dd_pct": 7.61
  },
  {
    "preset": "regime_keep_sideways",
    "note": "Bearish regime but keep sideways layer active.",
    "report_path": "/Users/naufalrachmandani/Library/Application Support/net.metaquotes.wine.metatrader5/drive_c/Program Files/MetaTrader 5/Reports/InvictusForward1M15_v8_round1_regime_keep_sideways_XAUUSDc_M15_20260101_20260415.htm",
    "net_profit": 28.94,
    "profit_pct": 28.939999999999998,
    "profit_factor": 1.85,
    "expected_payoff": 0.4,
    "total_trades": 73,
    "win_rate": 58.9,
    "balance_dd_pct": 7.06,
    "equity_dd_pct": 7.8
  },
  {
    "preset": "regime_adx28",
    "note": "Bearish regime requires stronger H4 ADX.",
    "report_path": "/Users/naufalrachmandani/Library/Application Support/net.metaquotes.wine.metatrader5/drive_c/Program Files/MetaTrader 5/Reports/InvictusForward1M15_v8_round1_regime_adx28_XAUUSDc_M15_20260101_20260415.htm",
    "net_profit": 30.04,
    "profit_pct": 30.04,
    "profit_factor": 1.89,
    "expected_payoff": 0.42,
    "total_trades": 72,
    "win_rate": 59.72,
    "balance_dd_pct": 7.02,
    "equity_dd_pct": 7.76
  },
  {
    "preset": "regime_soft_keep_sideways",
    "note": "Soft bearish regime while keeping sideways.",
    "report_path": "/Users/naufalrachmandani/Library/Application Support/net.metaquotes.wine.metatrader5/drive_c/Program Files/MetaTrader 5/Reports/InvictusForward1M15_v8_round1_regime_soft_keep_sideways_XAUUSDc_M15_20260101_20260415.htm",
    "net_profit": 28.7,
    "profit_pct": 28.7,
    "profit_factor": 1.84,
    "expected_payoff": 0.39,
    "total_trades": 73,
    "win_rate": 58.9,
    "balance_dd_pct": 7.32,
    "equity_dd_pct": 8.06
  },
  {
    "preset": "regime_hard_sell80",
    "note": "Hard bearish mode plus slightly looser sell min score.",
    "report_path": "/Users/naufalrachmandani/Library/Application Support/net.metaquotes.wine.metatrader5/drive_c/Program Files/MetaTrader 5/Reports/InvictusForward1M15_v8_round1_regime_hard_sell80_XAUUSDc_M15_20260101_20260415.htm",
    "net_profit": 0.0,
    "profit_pct": 0.0,
    "profit_factor": 0.0,
    "expected_payoff": 0.0,
    "total_trades": 0,
    "win_rate": 0.0,
    "balance_dd_pct": 0.0,
    "equity_dd_pct": 0.0
  }
]