[
  {
    "bot": "bull",
    "stem": "InvictusBullM5_v11",
    "set": "InvictusBullM5_v11.default_2026.set",
    "metrics": {
      "recent": {
        "net_profit": 39.97,
        "profit_factor": 3.63,
        "expected_payoff": 1.74,
        "total_trades": 23.0,
        "win_rate": 65.22,
        "balance_dd_abs": 4.32,
        "balance_dd_pct": 3.05,
        "equity_dd_abs": 7.29,
        "equity_dd_pct": 6.52
      },
      "ytd": {
        "net_profit": 269.58,
        "profit_factor": 2.37,
        "expected_payoff": 2.12,
        "total_trades": 127.0,
        "win_rate": 56.69,
        "balance_dd_abs": 27.51,
        "balance_dd_pct": 20.81,
        "equity_dd_abs": 48.87,
        "equity_dd_pct": 17.72
      }
    },
    "reports": {
      "recent": "/Users/naufalrachmandani/Library/Application Support/net.metaquotes.wine.metatrader5/drive_c/Program Files/MetaTrader 5/Reports/InvictusBullM5_v11_XAUUSDc_M5_20260401_20260425.htm",
      "ytd": "/Users/naufalrachmandani/Library/Application Support/net.metaquotes.wine.metatrader5/drive_c/Program Files/MetaTrader 5/Reports/InvictusBullM5_v11_XAUUSDc_M5_20260101_20260425.htm"
    }
  },
  {
    "bot": "bear",
    "stem": "InvictusBearM5_v11",
    "set": "InvictusBearM5_v11.default_2026.set",
    "metrics": {
      "recent": {
        "net_profit": 11.95,
        "profit_factor": 1.79,
        "expected_payoff": 0.8,
        "total_trades": 15.0,
        "win_rate": 60.0,
        "balance_dd_abs": 11.64,
        "balance_dd_pct": 9.67,
        "equity_dd_abs": 15.23,
        "equity_dd_pct": 12.56
      },
      "ytd": {
        "net_profit": 68.37,
        "profit_factor": 1.5,
        "expected_payoff": 0.79,
        "total_trades": 87.0,
        "win_rate": 55.17,
        "balance_dd_abs": 37.51,
        "balance_dd_pct": 31.45,
        "equity_dd_abs": 38.83,
        "equity_dd_pct": 32.25
      }
    },
    "reports": {
      "recent": "/Users/naufalrachmandani/Library/Application Support/net.metaquotes.wine.metatrader5/drive_c/Program Files/MetaTrader 5/Reports/InvictusBearM5_v11_XAUUSDc_M5_20260401_20260425.htm",
      "ytd": "/Users/naufalrachmandani/Library/Application Support/net.metaquotes.wine.metatrader5/drive_c/Program Files/MetaTrader 5/Reports/InvictusBearM5_v11_XAUUSDc_M5_20260101_20260425.htm"
    }
  },
  {
    "bot": "combined",
    "stem": "InvictusCombinedM5_v11",
    "set": "InvictusCombinedM5_v11.default_2026.set",
    "metrics": {
      "recent": {
        "net_profit": 40.25,
        "profit_factor": 3.12,
        "expected_payoff": 1.61,
        "total_trades": 25.0,
        "win_rate": 64.0,
        "balance_dd_abs": 5.38,
        "balance_dd_pct": 3.8,
        "equity_dd_abs": 10.44,
        "equity_dd_pct": 7.3
      },
      "ytd": {
        "net_profit": 558.51,
        "profit_factor": 2.7,
        "expected_payoff": 3.6,
        "total_trades": 155.0,
        "win_rate": 58.06,
        "balance_dd_abs": 27.51,
        "balance_dd_pct": 20.81,
        "equity_dd_abs": 51.64,
        "equity_dd_pct": 17.71
      }
    },
    "reports": {
      "recent": "/Users/naufalrachmandani/Library/Application Support/net.metaquotes.wine.metatrader5/drive_c/Program Files/MetaTrader 5/Reports/InvictusCombinedM5_v11_XAUUSDc_M5_20260401_20260425.htm",
      "ytd": "/Users/naufalrachmandani/Library/Application Support/net.metaquotes.wine.metatrader5/drive_c/Program Files/MetaTrader 5/Reports/InvictusCombinedM5_v11_XAUUSDc_M5_20260101_20260425.htm"
    }
  }
]